gopikachugo/__init__.py
gopikachugo/IMPORTANT/AJAX PROGRESS CONTROL AND TREE VIEW CONTROL EXAMPLE/ASPX1.pdf
gopikachugo/IMPORTANT/AJAX PROGRESS CONTROL AND TREE VIEW CONTROL EXAMPLE/ASPX2.pdf
gopikachugo/IMPORTANT/AJAX PROGRESS CONTROL AND TREE VIEW CONTROL EXAMPLE/CS1.pdf
gopikachugo/IMPORTANT/AJAX PROGRESS CONTROL AND TREE VIEW CONTROL EXAMPLE/CS2.pdf
gopikachugo/IMPORTANT/AJAX PROGRESS CONTROL AND TREE VIEW CONTROL EXAMPLE/SITEMAP2.pdf
gopikachugo/IMPORTANT/CONSOLE OPERATION AND CALENDOR CONTROL/ASPX.pdf
gopikachugo/IMPORTANT/CONSOLE OPERATION AND CALENDOR CONTROL/CONSOLE.pdf
gopikachugo/IMPORTANT/CONSOLE OPERATION AND CALENDOR CONTROL/CS.pdf
gopikachugo/IMPORTANT/DATE OPERATION AND STUDENT DETAILS SHOW USING GRIDVIEW/ASPX.pdf
gopikachugo/IMPORTANT/DATE OPERATION AND STUDENT DETAILS SHOW USING GRIDVIEW/ASPX2.pdf
gopikachugo/IMPORTANT/DATE OPERATION AND STUDENT DETAILS SHOW USING GRIDVIEW/CS.pdf
gopikachugo/IMPORTANT/DATE OPERATION AND STUDENT DETAILS SHOW USING GRIDVIEW/CS2.pdf
gopikachugo/IMPORTANT/DATE OPERATION AND STUDENT DETAILS SHOW USING GRIDVIEW/DB.pdf
gopikachugo/IMPORTANT/FIBONESIS PRIME NUMBER AND DATA ACCESS DISCONNECTED USING GRIDVIEW/ASPX.pdf
gopikachugo/IMPORTANT/FIBONESIS PRIME NUMBER AND DATA ACCESS DISCONNECTED USING GRIDVIEW/CS.pdf
gopikachugo/IMPORTANT/FIBONESIS PRIME NUMBER AND DATA ACCESS DISCONNECTED USING GRIDVIEW/PRIME AND FIBO.pdf
gopikachugo/IMPORTANT/JS BUTTON AND ADD MULTI SUB DIV USING TEXTBOX/ASPX.pdf
gopikachugo/IMPORTANT/JS BUTTON AND ADD MULTI SUB DIV USING TEXTBOX/ASPX2.pdf
gopikachugo/IMPORTANT/JS BUTTON AND ADD MULTI SUB DIV USING TEXTBOX/CS.pdf
gopikachugo/IMPORTANT/JS BUTTON AND ADD MULTI SUB DIV USING TEXTBOX/CS2.pdf
gopikachugo/IMPORTANT/MULTI INHERITENCE AND GRIDVIEW/ASPX.pdf
gopikachugo/IMPORTANT/MULTI INHERITENCE AND GRIDVIEW/CONSOLE.pdf
gopikachugo/IMPORTANT/MULTI INHERITENCE AND GRIDVIEW/CS.pdf
gopikachugo/IMPORTANT/MULTI INHERITENCE AND GRIDVIEW/DB.pdf
gopikachugo-0.1.0.dist-info/LICENSE
gopikachugo-0.1.0.dist-info/METADATA
gopikachugo-0.1.0.dist-info/WHEEL
gopikachugo-0.1.0.dist-info/top_level.txt
gopikachugo-0.1.0.dist-info/RECORD
